rfsyncer/__init__.py
rfsyncer/__main__.py
rfsyncer/cli.py
rfsyncer/commands/__init__.py
rfsyncer/commands/clear.py
rfsyncer/commands/diff.py
rfsyncer/commands/ping.py
rfsyncer/ssh/__init__.py
rfsyncer/ssh/connector.py
rfsyncer/syncer.py
rfsyncer/util/__init__.py
rfsyncer/util/config.py
rfsyncer/util/consts.py
rfsyncer/util/display.py
rfsyncer/util/exceptions.py
rfsyncer/util/hash.py
rfsyncer/util/logger.py
rfsyncer/util/parser.py
rfsyncer/util/types.py
rfsyncer-0.0.11.dist-info/WHEEL
rfsyncer-0.0.11.dist-info/entry_points.txt
rfsyncer-0.0.11.dist-info/METADATA
rfsyncer-0.0.11.dist-info/RECORD
