Metadata-Version: 2.4
Name: rfsyncer
Version: 0.0.11
Summary: A symple tool to make diffs and synchronize file trees.
Author: Headorteil
License-Expression: MIT
Requires-Dist: jinja2>=3.1.6
Requires-Dist: paramiko>=3.5.1
Requires-Dist: python-dotenv>=1.1.1
Requires-Dist: pyyaml>=6.0.2
Requires-Dist: rich>=14.0.0
Requires-Dist: typer>=0.16.0
Requires-Python: >=3.13
Project-URL: Repository, https://github.com/Headorteil/rfsyncer
